e2e.common-0.1.4-py3.10-nspkg.pth
e2e/common/__init__.py
e2e/common/modelling.py
e2e/common/py.typed
e2e/common/util.py
e2e.common-0.1.4.dist-info/LICENSE
e2e.common-0.1.4.dist-info/METADATA
e2e.common-0.1.4.dist-info/WHEEL
e2e.common-0.1.4.dist-info/namespace_packages.txt
e2e.common-0.1.4.dist-info/top_level.txt
e2e.common-0.1.4.dist-info/RECORD
