Metadata-Version: 2.1
Name: e2e.common
Version: 0.1.4
Summary: Core modelling framework components for the e2e package ecosystem
Home-page: https://github.com/nickroeker/e2e.common
Author: Nic Kroeker
License: Apache 2.0
Keywords: e2e,testing,framework,model
Classifier: Development Status :: 3 - Alpha
Classifier: Intended Audience :: Developers
Classifier: Programming Language :: Python
Classifier: Programming Language :: Python :: 3
Classifier: Programming Language :: Python :: 3.6
Classifier: Programming Language :: Python :: 3.7
Classifier: Programming Language :: Python :: 3.8
Classifier: Programming Language :: Python :: 3 :: Only
Classifier: Programming Language :: Python :: Implementation :: CPython
Classifier: Topic :: Software Development :: Testing
Classifier: Topic :: Software Development :: Testing :: Acceptance
Requires-Python: >=3.6
License-File: LICENSE
Provides-Extra: dev
Requires-Dist: pep8-naming ; extra == 'dev'
Requires-Dist: pylint ; extra == 'dev'
Requires-Dist: black ; extra == 'dev'
Requires-Dist: flake8 ; extra == 'dev'
Requires-Dist: tox ; extra == 'dev'
Requires-Dist: pytest ; extra == 'dev'
Requires-Dist: mypy ; extra == 'dev'
Requires-Dist: setuptools (>=40.6.0) ; extra == 'dev'
Requires-Dist: wheel ; extra == 'dev'
Requires-Dist: zest.releaser[recommended] ; extra == 'dev'
